automatic_incremental_uploads/__init__.py
automatic_incremental_uploads/__main__.py
automatic_incremental_uploads-0.1.0.dist-info/METADATA
automatic_incremental_uploads-0.1.0.dist-info/WHEEL
automatic_incremental_uploads-0.1.0.dist-info/entry_points.txt
automatic_incremental_uploads-0.1.0.dist-info/RECORD
