Metadata-Version: 2.1
Name: automatic-incremental-uploads
Version: 0.1.0
Summary: 
License: MIT
Author: Martin Ueding
Author-email: mu@martin-ueding.de
Requires-Python: >=3.11,<4.0
Classifier: License :: OSI Approved :: MIT License
Classifier: Programming Language :: Python :: 3
Classifier: Programming Language :: Python :: 3.11
Requires-Dist: inotify (>=0.2.10,<0.3.0)
